geoparsepy/__init__.py
geoparsepy/corpus-admintype-de.txt
geoparsepy/corpus-admintype-en.txt
geoparsepy/corpus-admintype-fr.txt
geoparsepy/corpus-admintype-it.txt
geoparsepy/corpus-admintype-pt.txt
geoparsepy/corpus-admintype-ru.txt
geoparsepy/corpus-buildingtype-en.txt
geoparsepy/corpus-buildingtype-fr.txt
geoparsepy/corpus-buildingtype-it.txt
geoparsepy/corpus-buildingtype-ru.txt
geoparsepy/corpus-geo-blacklist.txt
geoparsepy/corpus-geo-stoplist-de.txt
geoparsepy/corpus-geo-stoplist-en.txt
geoparsepy/corpus-geo-stoplist-fr.txt
geoparsepy/corpus-geo-stoplist-it.txt
geoparsepy/corpus-geo-stoplist-pt.txt
geoparsepy/corpus-geo-stoplist-ru.txt
geoparsepy/corpus-geo-whitelist.txt
geoparsepy/corpus-streettype-de.txt
geoparsepy/corpus-streettype-en.txt
geoparsepy/corpus-streettype-fr.txt
geoparsepy/corpus-streettype-it.txt
geoparsepy/corpus-streettype-pt.txt
geoparsepy/corpus-streettype-ru.txt
geoparsepy/gazeteer-en.txt
geoparsepy/geo_parse_lib.py
geoparsepy/geo_preprocess_lib.py
geoparsepy-2.1.4.dist-info/LICENSE.txt
geoparsepy-2.1.4.dist-info/METADATA
geoparsepy-2.1.4.dist-info/WHEEL
geoparsepy-2.1.4.dist-info/top_level.txt
geoparsepy-2.1.4.dist-info/RECORD
