Metadata-Version: 2.1
Name: geoparsepy
Version: 2.1.4
Summary: Geoparsing library to extract and disambiguate locations from text, using OSM database for very high throughputs and no rate limits
Home-page: http://www.ecs.soton.ac.uk/people/sem
Author: University of Southampton
Author-email: sem03@soton.ac.uk
License: BSD
Keywords: geoparse location extraction nlp geocode openstreetmap osm geo
Platform: UNKNOWN
Classifier: Development Status :: 6 - Mature
Classifier: Intended Audience :: Developers
Classifier: Topic :: Software Development :: Build Tools
Classifier: License :: OSI Approved :: BSD License
Classifier: Programming Language :: Python :: 3.7
Requires-Dist: nltk (>=3.4)
Requires-Dist: numpy (>=1.18)
Requires-Dist: shapely (>=1.6)
Requires-Dist: psycopg2 (>=2.8)
Requires-Dist: setuptools (>=46)
Requires-Dist: soton-corenlppy (>=1.0)
